xpypact/__init__.py
xpypact/collector.py
xpypact/dao/__init__.py
xpypact/dao/duckdb/__init__.py
xpypact/dao/duckdb/create_schema.sql
xpypact/dao/duckdb/implementation.py
xpypact/fluxes.py
xpypact/inventory.py
xpypact/nuclide.py
xpypact/py.typed
xpypact/time_step.py
xpypact/utils/__init__.py
xpypact/utils/xpypact_io.py
xpypact/xpypact_types.py
xpypact-0.12.9.dist-info/WHEEL
xpypact-0.12.9.dist-info/METADATA
xpypact-0.12.9.dist-info/RECORD
