Metadata-Version: 2.3
Name: xpypact
Version: 0.12.9
Summary: "Python workflow framework for FISPACT."
Keywords: nuclide,FISPACT,activation,duckdb,polars
Author: dvp2015
Author-email: dvp2015 <dmitri_portnov@yahoo.com>
License: MIT
Classifier: Development Status :: 4 - Beta
Classifier: Environment :: Console
Classifier: Intended Audience :: Developers
Classifier: Intended Audience :: Science/Research
Classifier: Operating System :: OS Independent
Classifier: Topic :: Scientific/Engineering :: Physics
Classifier: Programming Language :: Python :: 3
Requires-Dist: duckdb>=1.0.0
Requires-Dist: mckit-nuclides>=0.3.2
Requires-Dist: multipledispatch>=0.6.0
Requires-Dist: numpy>=2.3.1
Requires-Dist: polars[all]>=1.12.0
Requires-Dist: pyarrow>=18.0.0
Requires-Dist: msgspec>=0.19.0
Requires-Python: >=3.11, <3.14
Project-URL: Changelog, https://github.com/MC-kit/xpypact/releases
Project-URL: documentation, https://xpypact.readthedocs.io
Project-URL: homepage, https://github.com/MC-kit/xpypact
Project-URL: repository, https://github.com/MC-kit/xpypact
